log_candy/__init__.py
log_candy/log.py
log_candy-0.1.4.dist-info/licenses/LICENSE
log_candy-0.1.4.dist-info/METADATA
log_candy-0.1.4.dist-info/WHEEL
log_candy-0.1.4.dist-info/top_level.txt
log_candy-0.1.4.dist-info/RECORD
