Metadata-Version: 2.4
Name: log-candy
Version: 0.1.4
Summary: A simple Python logging utility for colorful terminal output
Home-page: https://github.com/SabeeenoGH/log-candy
Author: Sabino Roccotelli
Author-email: sabinoroccotelli@icloud.com
Classifier: Programming Language :: Python :: 3
Classifier: License :: OSI Approved :: MIT License
Classifier: Operating System :: OS Independent
Requires-Python: >=3.6
License-File: LICENSE
Dynamic: author
Dynamic: author-email
Dynamic: classifier
Dynamic: description
Dynamic: description-content-type
Dynamic: home-page
Dynamic: license-file
Dynamic: requires-python
Dynamic: summary
